easy_expectations/__init__.py
easy_expectations/__main__.py
easy_expectations/ai_expectations/__init__.py
easy_expectations/ai_expectations/core.py
easy_expectations/ai_expectations/data/__init__.py
easy_expectations/ai_expectations/data/datatypes.yaml
easy_expectations/ai_expectations/data/expectations_support.csv
easy_expectations/ai_expectations/flows/__init__.py
easy_expectations/ai_expectations/flows/base_conversation_flow.py
easy_expectations/ai_expectations/flows/profile_data_flow.py
easy_expectations/ai_expectations/flows/profiler_flow.py
easy_expectations/ai_expectations/flows/requirements_flow.py
easy_expectations/ai_expectations/flows.py
easy_expectations/ai_expectations/profiler_utils.py
easy_expectations/ai_expectations/usage_tracking.py
easy_expectations/cli/__init__.py
easy_expectations/cli/cli.py
easy_expectations/cli/cli_utils.py
easy_expectations/cli/data/__init__.py
easy_expectations/cli/data/empty_config_template.yaml
easy_expectations/config/__init__.py
easy_expectations/config/config.py
easy_expectations/config/config.yaml
easy_expectations/config_enhancer/__init__.py
easy_expectations/config_enhancer/data_systems_info.yaml
easy_expectations/config_enhancer/enhancer.py
easy_expectations/config_enhancer/strategies/__init__.py
easy_expectations/config_enhancer/strategies/backend_strategy.py
easy_expectations/config_enhancer/strategies/base_strategy.py
easy_expectations/config_enhancer/strategies/checkpoint_connector.py
easy_expectations/config_enhancer/strategies/credentials_strategy.py
easy_expectations/config_enhancer/strategies/default_batch_identifiers.py
easy_expectations/config_enhancer/strategies/default_naming_strategy.py
easy_expectations/config_enhancer/strategies/execution_engine_strategy.py
easy_expectations/config_enhancer/strategies/filesystem_enhancement_strategy.py
easy_expectations/config_enhancer/strategies/group_entities.py
easy_expectations/config_enhancer/strategies/inferred_connector_strategy.py
easy_expectations-0.1.0.dist-info/METADATA
easy_expectations-0.1.0.dist-info/WHEEL
easy_expectations-0.1.0.dist-info/entry_points.txt
easy_expectations-0.1.0.dist-info/RECORD
